damejson
