Metadata-Version: 1.1
Name: damejson
Version: 0.0.12
Summary: Learning Json from Tests by David Arroyo Menéndez
Home-page: http://github.com/davidam/damejson
Author: David Arroyo Menéndez
Author-email: davidam@gnu.org
License: GPLv3
Keywords: json tests
Platform: UNKNOWN
Classifier: Development Status :: 3 - Alpha
Classifier: License :: OSI Approved :: GNU General Public License v3 (GPLv3)
Classifier: Programming Language :: Python :: 3.6
Classifier: Topic :: Scientific/Engineering
